src/__init__.py
src/firewall_server.py
code_firewall_mcp-0.7.0.dist-info/METADATA
code_firewall_mcp-0.7.0.dist-info/WHEEL
code_firewall_mcp-0.7.0.dist-info/entry_points.txt
code_firewall_mcp-0.7.0.dist-info/licenses/LICENSE
code_firewall_mcp-0.7.0.dist-info/RECORD
