Metadata-Version: 2.4
Name: code-firewall-mcp
Version: 0.7.0
Summary: Code similarity firewall - blocks dangerous code patterns before they reach execution tools
Project-URL: Homepage, https://github.com/egoughnour/code-firewall-mcp
Project-URL: Repository, https://github.com/egoughnour/code-firewall-mcp
Author-email: Erik Goughnour <e.goughnour@gmail.com>
License: MIT
License-File: LICENSE
Keywords: code-analysis,embeddings,firewall,mcp,model-context-protocol,security,tree-sitter
Classifier: Development Status :: 3 - Alpha
Classifier: Intended Audience :: Developers
Classifier: License :: OSI Approved :: MIT License
Classifier: Programming Language :: Python :: 3
Classifier: Programming Language :: Python :: 3.10
Classifier: Programming Language :: Python :: 3.11
Classifier: Programming Language :: Python :: 3.12
Classifier: Programming Language :: Python :: 3.13
Classifier: Topic :: Security
Classifier: Topic :: Software Development :: Quality Assurance
Requires-Python: <3.14,>=3.10
Requires-Dist: chromadb>=0.4.0
Requires-Dist: fastmcp>=2.0.0
Requires-Dist: httpx>=0.27.0
Requires-Dist: tree-sitter-javascript>=0.21.0
Requires-Dist: tree-sitter-python>=0.21.0
Requires-Dist: tree-sitter>=0.21.0
Provides-Extra: dev
Requires-Dist: pytest-asyncio>=0.24.0; extra == 'dev'
Requires-Dist: pytest-cov>=4.0.0; extra == 'dev'
Requires-Dist: pytest>=8.0.0; extra == 'dev'
Requires-Dist: ruff>=0.1.0; extra == 'dev'
